task3/ram2ports.sv
module ram2ports # (
    parameter   A_WIDTH = 9,    // address width
                D_WIDTH = 8     // data width
)(
    input   logic               clk,
    input   logic               wr_en,
    input   logic               rd_en,
    input   logic [A_WIDTH-1:0] wr_addr,
    input   logic [A_WIDTH-1:0] rd_addr,
    input   logic [D_WIDTH-1:0] din,
    output  logic [D_WIDTH-1:0] dout
);

logic [D_WIDTH-1:0] ram_array [2 ** A_WIDTH-1:0];

always_ff @ (posedge clk) begin
    if (wr_en == 1'b1)
        ram_array[wr_addr] <= din;
    if (rd_en == 1'b1)
        // output is synchronous
        dout <= ram_array[rd_addr];
end
endmodule

task3/adder.sv
module adder #(
    parameter WIDTH = 9
)(
    input   logic               clk,
    input   logic               rst,
    input   logic [WIDTH-1:0]   a,
    input   logic [WIDTH-1:0]   b,
    output  logic [WIDTH-1:0]   c  
);

always_ff @ (posedge clk, posedge rst)
    if (rst)    c <= {WIDTH{1'b0}};
    else        c <= a + b;

endmodule

task3/counter.sv
module counter #(
    parameter WIDTH = 9
)(
    // interface signals
    input   logic               clk,    // clock
    input   logic               rst,    // reset
    input   logic               en,     // counter enable
    output  logic [WIDTH-1:0]   count   // counter output
);

always_ff @(posedge clk, posedge rst)
    if (rst)    count <= {WIDTH{1'b0}};
    else        count <= count + {{WIDTH{1'b0}}, en};

endmodule

task3/sigdelay.sv
module sigdelay # (
    parameter   WIDTH = 9
)(
    input   logic               clk,
    input   logic               rst,
    input   logic               en,
    input   logic               rd,
    input   logic               wr,
    input   logic [WIDTH-1:0]   offset,
    input   logic [WIDTH-1:0]   mic_signal,
    output  logic [WIDTH-1:0]   delayed_signal 
);

    wire    [WIDTH-1:0]         rd_addr;
    wire    [WIDTH-1:0]         wr_addr;

counter myCounter (
    .clk    (clk),
    .rst    (rst),
    .en     (en),
    .count  (rd_addr)
);

adder myAdder (
    .clk    (clk),
    .rst    (rst),
    .a      (wr_addr),
    .b      (offset),
    .c      (rd_addr)
);

ram2ports myRam (
    .clk        (clk),
    .wr_en      (wr),
    .rd_en      (rd),
    .wr_addr    (wr_addr),
    .rd_addr    (rd_addr),
    .din        (mic_signal),
    .dout       (delayed_signal)
);

endmodule

task3/sigdelay.vcd
$version Generated by VerilatedVcd $end
$date Thu Nov  3 14:35:55 2022 $end
$timescale 1ps $end

 $scope module TOP $end
  $var wire  1 # clk $end
  $var wire  9 * delayed_signal [8:0] $end
  $var wire  1 % en $end
  $var wire  9 ) mic_signal [8:0] $end
  $var wire  9 ( offset [8:0] $end
  $var wire  1 & rd $end
  $var wire  1 $ rst $end
  $var wire  1 ' wr $end
  $scope module sigdelay $end
   $var wire 32 . WIDTH [31:0] $end
   $var wire  1 # clk $end
   $var wire  9 * delayed_signal [8:0] $end
   $var wire  1 % en $end
   $var wire  9 ) mic_signal [8:0] $end
   $var wire  9 ( offset [8:0] $end
   $var wire  1 & rd $end
   $var wire  9 + rd_addr [8:0] $end
   $var wire  1 $ rst $end
   $var wire  1 ' wr $end
   $var wire  9 / wr_addr [8:0] $end
   $scope module myAdder $end
    $var wire 32 . WIDTH [31:0] $end
    $var wire  9 / a [8:0] $end
    $var wire  9 ( b [8:0] $end
    $var wire  9 + c [8:0] $end
    $var wire  1 # clk $end
    $var wire  1 $ rst $end
   $upscope $end
   $scope module myCounter $end
    $var wire 32 . WIDTH [31:0] $end
    $var wire  1 # clk $end
    $var wire  9 + count [8:0] $end
    $var wire  1 % en $end
    $var wire  1 $ rst $end
   $upscope $end
   $scope module myRam $end
    $var wire 32 . A_WIDTH [31:0] $end
    $var wire 32 0 D_WIDTH [31:0] $end
    $var wire  1 # clk $end
    $var wire  8 , din [7:0] $end
    $var wire  8 - dout [7:0] $end
    $var wire  9 + rd_addr [8:0] $end
    $var wire  1 & rd_en $end
    $var wire  9 / wr_addr [8:0] $end
    $var wire  1 ' wr_en $end
   $upscope $end
  $upscope $end
 $upscope $end
$enddefinitions $end


#0
1#
0$
0%
1&
1'
b001000000 (
b000000000 )
b000000000 *
b000000000 +
b00000000 ,
b00000000 -
b00000000000000000000000000001001 .
b000000000 /
b00000000000000000000000000001000 0
#1
0#
#2
1#
b000100011 (
b010100001 )
b10100001 ,
#3
0#
#4
1#
b001010011 )
b01010011 ,
#5
0#
#6
1#
b000101100 )
b010100001 *
b00101100 ,
b10100001 -
#7
0#
#8
1#
b001101010 )
b001010011 *
b01101010 ,
b01010011 -
#9
0#
#10
1#
b010011100 )
b000101100 *
b10011100 ,
b00101100 -
#11
0#
#12
1#
b001110011 )
b001101010 *
b01110011 ,
b01101010 -
#13
0#
#14
1#
b001100001 )
b010011100 *
b01100001 ,
b10011100 -
#15
0#
#16
1#
b001111011 )
b001110011 *
b01111011 ,
b01110011 -
#17
0#
#18
1#
b001111100 )
b001100001 *
b01111100 ,
b01100001 -
#19
0#
#20
1#
b001001100 )
b001111011 *
b01001100 ,
b01111011 -
#21
0#
#22
1#
b000110100 )
b001111100 *
b00110100 ,
b01111100 -
#23
0#
#24
1#
b001101000 )
b001001100 *
b01101000 ,
b01001100 -
#25
0#
#26
1#
b001111001 )
b000110100 *
b01111001 ,
b00110100 -
#27
0#
#28
1#
b001101100 )
b001101000 *
b01101100 ,
b01101000 -
#29
0#
#30
1#
b001011111 )
b001111001 *
b01011111 ,
b01111001 -
#31
0#
#32
1#
b001101001 )
b001101100 *
b01101001 ,
b01101100 -
#33
0#
#34
1#
b001100001 )
b001011111 *
b01100001 ,
b01011111 -
#35
0#
#36
1#
b001011010 )
b001101001 *
b01011010 ,
b01101001 -
#37
0#
#38
1#
b001110100 )
b001100001 *
b01110100 ,
b01100001 -
#39
0#
#40
1#
b010000111 )
b001011010 *
b10000111 ,
b01011010 -
#41
0#
#42
1#
b001101010 )
b001110100 *
b01101010 ,
b01110100 -
#43
0#
#44
1#
b001001011 )
b010000111 *
b01001011 ,
b10000111 -
#45
0#
#46
1#
b001101010 )
b001101010 *
b01101010 ,
b01101010 -
#47
0#
#48
1#
b001110000 )
b001001011 *
b01110000 ,
b01001011 -
#49
0#
#50
1#
b001101010 )
b001101010 *
b01101010 ,
b01101010 -
#51
0#
#52
1#
b001100100 )
b001110000 *
b01100100 ,
b01110000 -
#53
0#
#54
1#
b001111100 )
b001101010 *
b01111100 ,
b01101010 -
#55
0#
#56
1#
b001101100 )
b001100100 *
b01101100 ,
b01100100 -
#57
0#
#58
1#
b001100000 )
b001111100 *
b01100000 ,
b01111100 -
#59
0#
#60
1#
b001011101 )
b001101100 *
b01011101 ,
b01101100 -
#61
0#
#62
1#
b001110000 )
b001100000 *
b01110000 ,
b01100000 -
#63
0#
#64
1#
b001101010 )
b001011101 *
b01101010 ,
b01011101 -
#65
0#
#66
1#
b001100110 )
b001110000 *
b01100110 ,
b01110000 -
#67
0#
#68
1#
b001100011 )
b001101010 *
b01100011 ,
b01101010 -
#69
0#
#70
1#
b001100110 *
b01100110 -
#71
0#
#72
1#
b001100110 )
b001100011 *
b01100110 ,
b01100011 -
#73
0#
#74
1#
b001101000 )
b01101000 ,
#75
0#
#76
1#
b001100101 )
b001100110 *
b01100101 ,
b01100110 -
#77
0#
#78
1#
b001100110 )
b001101000 *
b01100110 ,
b01101000 -
#79
0#
#80
1#
b001100010 )
b001100101 *
b01100010 ,
b01100101 -
#81
0#
#82
1#
b001100011 )
b001100110 *
b01100011 ,
b01100110 -
#83
0#
#84
1#
b001101000 )
b001100010 *
b01101000 ,
b01100010 -
#85
0#
#86
1#
b001101001 )
b001100011 *
b01101001 ,
b01100011 -
#87
0#
#88
1#
b001100101 )
b001101000 *
b01100101 ,
b01101000 -
#89
0#
#90
1#
b001100011 )
b001101001 *
b01100011 ,
b01101001 -
#91
0#
#92
1#
b001011101 )
b001100101 *
b01011101 ,
b01100101 -
#93
0#
#94
1#
b001011011 )
b001100011 *
b01011011 ,
b01100011 -
#95
0#
#96
1#
b001011010 )
b001011101 *
b01011010 ,
b01011101 -
#97
0#
#98
1#
b001011110 )
b001011011 *
b01011110 ,
b01011011 -
#99
0#
#100
1#
b001011010 *
b01011010 -
#101
0#
#102
1#
b001011110 *
b01011110 -
#103
0#
#104
1#
b001011100 )
b01011100 ,
#105
0#
#106
1#
b001011001 )
b01011001 ,
#107
0#
#108
1#
b001010111 )
b001011100 *
b01010111 ,
b01011100 -
#109
0#
#110
1#
b001011110 )
b001011001 *
b01011110 ,
b01011001 -
#111
0#
#112
1#
b001011011 )
b001010111 *
b01011011 ,
b01010111 -
#113
0#
#114
1#
b001100011 )
b001011110 *
b01100011 ,
b01011110 -
#115
0#
#116
1#
b001101001 )
b001011011 *
b01101001 ,
b01011011 -
#117
0#
#118
1#
b001101110 )
b001100011 *
b01101110 ,
b01100011 -
#119
0#
#120
1#
b001110000 )
b001101001 *
b01110000 ,
b01101001 -
#121
0#
#122
1#
b001111000 )
b001101110 *
b01111000 ,
b01101110 -
#123
0#
#124
1#
b010000000 )
b001110000 *
b10000000 ,
b01110000 -
#125
0#
#126
1#
b001111101 )
b001111000 *
b01111101 ,
b01111000 -
#127
0#
#128
1#
b001111100 )
b010000000 *
b01111100 ,
b10000000 -
#129
0#
#130
1#
b001111001 )
b001111101 *
b01111001 ,
b01111101 -
#131
0#
#132
1#
b001111010 )
b001111100 *
b01111010 ,
b01111100 -
#133
0#
#134
1#
b001110101 )
b001111001 *
b01110101 ,
b01111001 -
#135
0#
#136
1#
b001110010 )
b001111010 *
b01110010 ,
b01111010 -
#137
0#
#138
1#
b001110100 )
b001110101 *
b01110100 ,
b01110101 -
#139
0#
#140
1#
b001110110 )
b001110010 *
b01110110 ,
b01110010 -
#141
0#
#142
1#
b001110100 *
b01110100 -
#143
0#
#144
1#
b001110111 )
b001110110 *
b01110111 ,
b01110110 -
#145
0#
#146
1#
b001110100 )
b01110100 ,
#147
0#
#148
1#
b001101111 )
b001110111 *
b01101111 ,
b01110111 -
#149
0#
#150
1#
b001100110 )
b001110100 *
b01100110 ,
b01110100 -
#151
0#
#152
1#
b001100010 )
b001101111 *
b01100010 ,
b01101111 -
#153
0#
#154
1#
b001100011 )
b001100110 *
b01100011 ,
b01100110 -
#155
0#
#156
1#
b001011110 )
b001100010 *
b01011110 ,
b01100010 -
#157
0#
#158
1#
b001100100 )
b001100011 *
b01100100 ,
b01100011 -
#159
0#
#160
1#
b001011110 *
b01011110 -
#161
0#
#162
1#
b001100101 )
b001100100 *
b01100101 ,
b01100100 -
#163
0#
#164
1#
b001100110 )
b01100110 ,
#165
0#
#166
1#
b001101010 )
b001100101 *
b01101010 ,
b01100101 -
#167
0#
#168
1#
b001101101 )
b001100110 *
b01101101 ,
b01100110 -
#169
0#
#170
1#
b000100101 (
b001101010 *
b01101010 -
#171
0#
#172
1#
b000101000 (
b001101111 )
b001101101 *
b01101111 ,
b01101101 -
#173
0#
#174
1#
b000101010 (
b001110000 )
b01110000 ,
#175
0#
#176
1#
b000101100 (
b001101111 *
b01101111 -
#177
0#
#178
1#
b000101101 (
b001101111 )
b001110000 *
b01101111 ,
b01110000 -
#179
0#
#180
1#
b001110010 )
b01110010 ,
#181
0#
#182
1#
b000101110 (
b001110011 )
b001101111 *
b01110011 ,
b01101111 -
#183
0#
#184
1#
b000101111 (
b001110110 )
b001110010 *
b01110110 ,
b01110010 -
#185
0#
#186
1#
b000110000 (
b001111001 )
b001110011 *
b01111001 ,
b01110011 -
#187
0#
#188
1#
b000110001 (
b001111000 )
b001110110 *
b01111000 ,
b01110110 -
#189
0#
#190
1#
b000110010 (
b001110011 )
b001111001 *
b01110011 ,
b01111001 -
#191
0#
#192
1#
b000110100 (
b001101101 )
b001111000 *
b01101101 ,
b01111000 -
#193
0#
#194
1#
b000110101 (
b001101011 )
b001110011 *
b01101011 ,
b01110011 -
#195
0#
#196
1#
b000110111 (
b001101100 )
b001101101 *
b01101100 ,
b01101101 -
#197
0#
#198
1#
b000111001 (
b001101110 )
b001101011 *
b01101110 ,
b01101011 -
#199
0#
#200
1#
b001110001 )
b001101100 *
b01110001 ,
b01101100 -
#201
0#
#202
1#
b000111100 (
b001101101 )
b001101110 *
b01101101 ,
b01101110 -
#203
0#
#204
1#
b001101111 )
b001110001 *
b01101111 ,
b01110001 -
#205
0#
#206
1#
b000111101 (
b001110101 )
b001101101 *
b01110101 ,
b01101101 -
#207
0#
#208
1#
b000111110 (
b001111000 )
b001101111 *
b01111000 ,
b01101111 -
#209
0#
#210
1#
b001110110 )
b001110101 *
b01110110 ,
b01110101 -
#211
0#
#212
1#
b001110111 )
b001111000 *
b01110111 ,
b01111000 -
#213
0#
#214
1#
b001110110 )
b001110110 *
b01110110 ,
b01110110 -
#215
0#
#216
1#
b001110011 )
b001110111 *
b01110011 ,
b01110111 -
#217
0#
#218
1#
b001110001 )
b001110110 *
b01110001 ,
b01110110 -
#219
0#
#220
1#
b001110011 )
b001110011 *
b01110011 ,
b01110011 -
#221
0#
#222
1#
b001110111 )
b001110001 *
b01110111 ,
b01110001 -
#223
0#
#224
1#
b001111101 )
b001110011 *
b01111101 ,
b01110011 -
#225
0#
#226
1#
b010000000 )
b001110111 *
b10000000 ,
b01110111 -
#227
0#
#228
1#
b010000001 )
b001111101 *
b10000001 ,
b01111101 -
#229
0#
#230
1#
b010000100 )
b010000000 *
b10000100 ,
b10000000 -
#231
0#
#232
1#
b010000010 )
b010000001 *
b10000010 ,
b10000001 -
#233
0#
#234
1#
b010000101 )
b010000100 *
b10000101 ,
b10000100 -
#235
0#
#236
1#
b010000010 *
b10000010 -
#237
0#
#238
1#
b010000100 )
b010000101 *
b10000100 ,
b10000101 -
#239
0#
#240
1#
b010000010 )
b10000010 ,
#241
0#
#242
1#
b010000100 )
b010000100 *
b10000100 ,
b10000100 -
#243
0#
#244
1#
b001000000 (
b010000010 )
b010000010 *
b10000010 ,
b10000010 -
#245
0#
#246
1#
b001000110 (
b001111110 )
b010000100 *
b01111110 ,
b10000100 -
#247
0#
#248
1#
b001001001 (
b001111100 )
b010000010 *
b01111100 ,
b10000010 -
#249
0#
#250
1#
b001001011 (
b001111001 )
b001111110 *
b01111001 ,
b01111110 -
#251
0#
#252
1#
b001001100 (
b001110001 )
b001111100 *
b01110001 ,
b01111100 -
#253
0#
#254
1#
b001001101 (
b001101111 )
b001111001 *
b01101111 ,
b01111001 -
#255
0#
#256
1#
b001001110 (
b001101110 )
b001110001 *
b01101110 ,
b01110001 -
#257
0#
#258
1#
b001001111 (
b001101111 )
b001101111 *
b01101111 ,
b01101111 -
#259
0#
#260
1#
b001010000 (
b001101001 )
b001101110 *
b01101001 ,
b01101110 -
#261
0#
#262
1#
b001010010 (
b001100111 )
b001101111 *
b01100111 ,
b01101111 -
#263
0#
#264
1#
b001010011 (
b001101001 *
b01101001 -
#265
0#
#266
1#
b001010101 (
b001100110 )
b001100111 *
b01100110 ,
b01100111 -
#267
0#
#268
1#
b001010110 (
b001100010 )
b01100010 ,
#269
0#
#270
1#
b001010111 (
b001100011 )
b001100110 *
b01100011 ,
b01100110 -
#271
0#
#272
1#
b001100010 *
b01100010 -
#273
0#
#274
1#
b001100000 )
b001100011 *
b01100000 ,
b01100011 -
#275
0#
#276
1#
b001011101 )
b01011101 ,
#277
0#
#278
1#
b001011111 )
b001100000 *
b01011111 ,
b01100000 -
#279
0#
#280
1#
b001011000 )
b001011101 *
b01011000 ,
b01011101 -
#281
0#
#282
1#
b001011001 )
b001011111 *
b01011001 ,
b01011111 -
#283
0#
#284
1#
b001011011 )
b001011000 *
b01011011 ,
b01011000 -
#285
0#
#286
1#
b001011010 )
b001011001 *
b01011010 ,
b01011001 -
#287
0#
#288
1#
b001011011 *
b01011011 -
#289
0#
#290
1#
b001011011 )
b001011010 *
b01011011 ,
b01011010 -
#291
0#
#292
1#
b001011010 )
b01011010 ,
#293
0#
#294
1#
b001011110 )
b001011011 *
b01011110 ,
b01011011 -
#295
0#
#296
1#
b001011100 )
b001011010 *
b01011100 ,
b01011010 -
#297
0#
#298
1#
b001010110 )
b001011110 *
b01010110 ,
b01011110 -
#299
0#
#300
1#
b001010000 )
b001011100 *
b01010000 ,
b01011100 -
#301
0#
#302
1#
b001010100 )
b001010110 *
b01010100 ,
b01010110 -
#303
0#
#304
1#
b001010101 )
b001010000 *
b01010101 ,
b01010000 -
#305
0#
#306
1#
b001010100 *
b01010100 -
#307
0#
#308
1#
b001011011 )
b001010101 *
b01011011 ,
b01010101 -
#309
0#
#310
1#
b001011100 )
b01011100 ,
#311
0#
#312
1#
b001011011 *
b01011011 -
#313
0#
#314
1#
b001011110 )
b001011100 *
b01011110 ,
b01011100 -
#315
0#
#316
1#
b001100111 )
b01100111 ,
#317
0#
#318
1#
b001101001 )
b001011110 *
b01101001 ,
b01011110 -
#319
0#
#320
1#
b001101101 )
b001100111 *
b01101101 ,
b01100111 -
#321
0#
#322
1#
b001101110 )
b001101001 *
b01101110 ,
b01101001 -
#323
0#
#324
1#
b001110100 )
b001101101 *
b01110100 ,
b01101101 -
#325
0#
#326
1#
b001110111 )
b001101110 *
b01110111 ,
b01101110 -
#327
0#
#328
1#
b001111001 )
b001110100 *
b01111001 ,
b01110100 -
#329
0#
#330
1#
b001111100 )
b001110111 *
b01111100 ,
b01110111 -
#331
0#
#332
1#
b001111001 *
b01111001 -
#333
0#
#334
1#
b001111011 )
b001111100 *
b01111011 ,
b01111100 -
#335
0#
#336
1#
b001111000 )
b01111000 ,
#337
0#
#338
1#
b001111001 )
b001111011 *
b01111001 ,
b01111011 -
#339
0#
#340
1#
b001110101 )
b001111000 *
b01110101 ,
b01111000 -
#341
0#
#342
1#
b001110000 )
b001111001 *
b01110000 ,
b01111001 -
#343
0#
#344
1#
b001101100 )
b001110101 *
b01101100 ,
b01110101 -
#345
0#
#346
1#
b001101111 )
b001110000 *
b01101111 ,
b01110000 -
#347
0#
#348
1#
b001110000 )
b001101100 *
b01110000 ,
b01101100 -
#349
0#
#350
1#
b001110110 )
b001101111 *
b01110110 ,
b01101111 -
#351
0#
#352
1#
b001110100 )
b001110000 *
b01110100 ,
b01110000 -
#353
0#
#354
1#
b001110111 )
b001110110 *
b01110111 ,
b01110110 -
#355
0#
#356
1#
b001110011 )
b001110100 *
b01110011 ,
b01110100 -
#357
0#
#358
1#
b001110111 )
b001110111 *
b01110111 ,
b01110111 -
#359
0#
#360
1#
b001111000 )
b001110011 *
b01111000 ,
b01110011 -
#361
0#
#362
1#
b001111110 )
b001110111 *
b01111110 ,
b01110111 -
#363
0#
#364
1#
b001111111 )
b001111000 *
b01111111 ,
b01111000 -
#365
0#
#366
1#
b001111101 )
b001111110 *
b01111101 ,
b01111110 -
#367
0#
#368
1#
b010000001 )
b001111111 *
b10000001 ,
b01111111 -
#369
0#
#370
1#
b010000000 )
b001111101 *
b10000000 ,
b01111101 -
#371
0#
#372
1#
b001111011 )
b010000001 *
b01111011 ,
b10000001 -
#373
0#
#374
1#
b001110111 )
b010000000 *
b01110111 ,
b10000000 -
#375
0#
#376
1#
b001110101 )
b001111011 *
b01110101 ,
b01111011 -
#377
0#
#378
1#
b001110000 )
b001110111 *
b01110000 ,
b01110111 -
#379
0#
#380
1#
b001110110 )
b001110101 *
b01110110 ,
b01110101 -
#381
0#
#382
1#
b001110010 )
b001110000 *
b01110010 ,
b01110000 -
#383
0#
#384
1#
b001010110 (
b001110100 )
b001110110 *
b01110100 ,
b01110110 -
#385
0#
#386
1#
b001010101 (
b001111000 )
b001110010 *
b01111000 ,
b01110010 -
#387
0#
#388
1#
b001010100 (
b001111100 )
b001110100 *
b01111100 ,
b01110100 -
#389
0#
#390
1#
b001010010 (
b001111000 *
b01111000 -
#391
0#
#392
1#
b001001111 (
b010000000 )
b001111100 *
b10000000 ,
b01111100 -
#393
0#
#394
1#
b001001010 (
b010000001 )
b10000001 ,
#395
0#
#396
1#
b001000111 (
b010000000 *
b10000000 -
#397
0#
#398
1#
b010000001 *
b10000001 -
#399
0#
#400
1#
b001111100 )
b01111100 ,
#401
0#
#402
1#
#403
0#
#404
1#
b001110110 )
b001111100 *
b01110110 ,
b01111100 -
#405
0#
#406
1#
b001101110 )
b01101110 ,
#407
0#
#408
1#
b001100111 )
b001110110 *
b01100111 ,
b01110110 -
#409
0#
#410
1#
b001100101 )
b001101110 *
b01100101 ,
b01101110 -
#411
0#
#412
1#
b001100110 )
b001100111 *
b01100110 ,
b01100111 -
#413
0#
#414
1#
b001100101 *
b01100101 -
#415
0#
#416
1#
b001101110 )
b001100110 *
b01101110 ,
b01100110 -
#417
0#
#418
1#
b001000011 (
b001110000 )
b01110000 ,
#419
0#
#420
1#
b001000001 (
b001110010 )
b001101110 *
b01110010 ,
b01101110 -
#421
0#
#422
1#
b001000000 (
b001110100 )
b001110000 *
b01110100 ,
b01110000 -
#423
0#
#424
1#
b000111101 (
b001110101 )
b001110010 *
b01110101 ,
b01110010 -
#425
0#
#426
1#
b000110111 (
b001110100 *
b01110100 -
#427
0#
#428
1#
b001110000 )
b001110101 *
b01110000 ,
b01110101 -
#429
0#
#430
1#
#431
0#
#432
1#
b001110001 )
b001110000 *
b01110001 ,
b01110000 -
#433
0#
#434
1#
b001101111 )
b01101111 ,
#435
0#
#436
1#
b001110001 *
b01110001 -
#437
0#
#438
1#
b001101010 )
b001101111 *
b01101010 ,
b01101111 -
#439
0#
#440
1#
b001100111 )
b01100111 ,
#441
0#
#442
1#
b001100101 )
b001101010 *
b01100101 ,
b01101010 -
#443
0#
#444
1#
b001100111 *
b01100111 -
#445
0#
#446
1#
b001101011 )
b001100101 *
b01101011 ,
b01100101 -
#447
0#
#448
1#
b001101110 )
b01101110 ,
#449
0#
#450
1#
b001110010 )
b001101011 *
b01110010 ,
b01101011 -
#451
0#
#452
1#
b000110110 (
b001101110 )
b001101110 *
b01101110 ,
b01101110 -
#453
0#
#454
1#
b000110100 (
b001101010 )
b001110010 *
b01101010 ,
b01110010 -
#455
0#
#456
1#
b000110000 (
b001100110 )
b001101110 *
b01100110 ,
b01101110 -
#457
0#
#458
1#
b000101110 (
b001100101 )
b001101010 *
b01100101 ,
b01101010 -
#459
0#
#460
1#
b001100100 )
b001100110 *
b01100100 ,
b01100110 -
#461
0#
#462
1#
b001101000 )
b001100101 *
b01101000 ,
b01100101 -
#463
0#
#464
1#
b001101001 )
b001100100 *
b01101001 ,
b01100100 -
#465
0#
#466
1#
b001101011 )
b001101000 *
b01101011 ,
b01101000 -
#467
0#
#468
1#
b001101101 )
b001101001 *
b01101101 ,
b01101001 -
#469
0#
#470
1#
b001110011 )
b001101011 *
b01110011 ,
b01101011 -
#471
0#
#472
1#
b001110010 )
b001101101 *
b01110010 ,
b01101101 -
#473
0#
#474
1#
b001110011 *
b01110011 -
#475
0#
#476
1#
b001101011 )
b001110010 *
b01101011 ,
b01110010 -
#477
0#
#478
1#
b000101101 (
b001101001 )
b01101001 ,
#479
0#
#480
1#
b000101100 (
b001101010 )
b001101011 *
b01101010 ,
b01101011 -
#481
0#
#482
1#
b000101011 (
b001100100 )
b001101001 *
b01100100 ,
b01101001 -
#483
0#
#484
1#
b000101000 (
b001100010 )
b001101010 *
b01100010 ,
b01101010 -
#485
0#
#486
1#
b001100001 )
b001100100 *
b01100001 ,
b01100100 -
#487
0#
#488
1#
b000100111 (
b001100111 )
b001100010 *
b01100111 ,
b01100010 -
#489
0#
#490
1#
b001100100 )
b001100001 *
b01100100 ,
b01100001 -
#491
0#
#492
1#
b001100101 )
b001100111 *
b01100101 ,
b01100111 -
#493
0#
#494
1#
b001100100 *
b01100100 -
#495
0#
#496
1#
b001101000 )
b001100101 *
b01101000 ,
b01100101 -
#497
0#
#498
1#
b001101011 )
b01101011 ,
#499
0#
#500
1#
b001101100 )
b001101000 *
b01101100 ,
b01101000 -
#501
0#
#502
1#
b001110110 )
b001101011 *
b01110110 ,
b01101011 -
#503
0#
#504
1#
b001111000 )
b001101100 *
b01111000 ,
b01101100 -
#505
0#
#506
1#
b001110111 )
b001110110 *
b01110111 ,
b01110110 -
#507
0#
#508
1#
b001111101 )
b001111000 *
b01111101 ,
b01111000 -
#509
0#
#510
1#
b000100110 (
b001111100 )
b001110111 *
b01111100 ,
b01110111 -
#511
0#
#512
1#
b000100011 (
b001111010 )
b001111101 *
b01111010 ,
b01111101 -
#513
0#
#514
1#
b000100010 (
b001111100 *
b01111100 -
#515
0#
#516
1#
b001110101 )
b001111010 *
b01110101 ,
b01111010 -
#517
0#
#518
1#
b000100000 (
b001110100 )
b01110100 ,
#519
0#
#520
1#
b000011111 (
b001110011 )
b001110101 *
b01110011 ,
b01110101 -
#521
0#
#522
1#
b000011110 (
b001101111 )
b001110100 *
b01101111 ,
b01110100 -
#523
0#
#524
1#
b001101100 )
b001110011 *
b01101100 ,
b01110011 -
#525
0#
#526
1#
b001101101 )
b001101111 *
b01101101 ,
b01101111 -
#527
0#
#528
1#
b001101011 )
b001101100 *
b01101011 ,
b01101100 -
#529
0#
#530
1#
b001101101 )
b001101101 *
b01101101 ,
b01101101 -
#531
0#
#532
1#
b001101011 )
b001101011 *
b01101011 ,
b01101011 -
#533
0#
#534
1#
b001101111 )
b001101101 *
b01101111 ,
b01101101 -
#535
0#
#536
1#
b001101010 )
b001101011 *
b01101010 ,
b01101011 -
#537
0#
#538
1#
b000011101 (
b001110010 )
b001101111 *
b01110010 ,
b01101111 -
#539
0#
#540
1#
b001110001 )
b001101010 *
b01110001 ,
b01101010 -
#541
0#
#542
1#
b000011100 (
b001110011 )
b001110010 *
b01110011 ,
b01110010 -
#543
0#
#544
1#
b001110001 )
b001110001 *
b01110001 ,
b01110001 -
#545
0#
#546
1#
b001110010 )
b001110011 *
b01110010 ,
b01110011 -
#547
0#
#548
1#
b001101001 )
b001110001 *
b01101001 ,
b01110001 -
#549
0#
#550
1#
b001101011 )
b001110010 *
b01101011 ,
b01110010 -
#551
0#
#552
1#
b001100011 )
b001101001 *
b01100011 ,
b01101001 -
#553
0#
#554
1#
b001100000 )
b001101011 *
b01100000 ,
b01101011 -
#555
0#
#556
1#
b001011110 )
b001100011 *
b01011110 ,
b01100011 -
#557
0#
#558
1#
b001100000 )
b001100000 *
b01100000 ,
b01100000 -
#559
0#
#560
1#
b001100011 )
b001011110 *
b01100011 ,
b01011110 -
#561
0#
#562
1#
b001100101 )
b001100000 *
b01100101 ,
b01100000 -
#563
0#
#564
1#
b001101001 )
b001100011 *
b01101001 ,
b01100011 -
#565
0#
#566
1#
b001101110 )
b001100101 *
b01101110 ,
b01100101 -
#567
0#
#568
1#
b000011010 (
b001110000 )
b001101001 *
b01110000 ,
b01101001 -
#569
0#
#570
1#
b000011001 (
b001100111 )
b001101110 *
b01100111 ,
b01101110 -
#571
0#
#572
1#
b000010101 (
b001101010 )
b001110000 *
b01101010 ,
b01110000 -
#573
0#
#574
1#
b000010001 (
b001101001 )
b001100111 *
b01101001 ,
b01100111 -
#575
0#
#576
1#
b001100101 )
b001101010 *
b01100101 ,
b01101010 -
#577
0#
#578
1#
b001100010 )
b001101001 *
b01100010 ,
b01101001 -
#579
0#
#580
1#
b001100001 )
b001100101 *
b01100001 ,
b01100101 -
#581
0#
#582
1#
b001100010 *
b01100010 -
#583
0#
#584
1#
b001100100 )
b001100001 *
b01100100 ,
b01100001 -
#585
0#
#586
1#
b001100110 )
b01100110 ,
#587
0#
#588
1#
b001110000 )
b001100100 *
b01110000 ,
b01100100 -
#589
0#
#590
1#
b001110010 )
b001100110 *
b01110010 ,
b01100110 -
#591
0#
#592
1#
b001110101 )
b001110000 *
b01110101 ,
b01110000 -
#593
0#
#594
1#
b001110111 )
b001110010 *
b01110111 ,
b01110010 -
#595
0#
#596
1#
b000010000 (
b001110101 )
b001110101 *
b01110101 ,
b01110101 -
#597
0#
#598
1#
b000001110 (
b001110001 )
b001110111 *
b01110001 ,
b01110111 -
#599
0#
#600
1#
b000001010 (
b001110100 )
b001110101 *
b01110100 ,
b01110101 -
#601
0#
#602
1#
b000001001 (
b001110011 )
b001110001 *
b01110011 ,
b01110001 -
#603
0#
#604
1#
b001110010 )
b001110100 *
b01110010 ,
b01110100 -
#605
0#
#606
1#
b001110101 )
b001110011 *
b01110101 ,
b01110011 -
#607
0#
#608
1#
b001110011 )
b001110010 *
b01110011 ,
b01110010 -
#609
0#
#610
1#
b001110100 )
b001110101 *
b01110100 ,
b01110101 -
#611
0#
#612
1#
b001110000 )
b001110011 *
b01110000 ,
b01110011 -
#613
0#
#614
1#
b001110100 *
b01110100 -
#615
0#
#616
1#
b001110000 *
b01110000 -
#617
0#
#618
1#
b001110101 )
b01110101 ,
#619
0#
#620
1#
b001110000 )
b01110000 ,
#621
0#
#622
1#
b001110001 )
b001110101 *
b01110001 ,
b01110101 -
#623
0#
#624
1#
b000000110 (
b001110010 )
b001110000 *
b01110010 ,
b01110000 -
#625
0#
#626
1#
b001101101 )
b001110001 *
b01101101 ,
b01110001 -
#627
0#
#628
1#
b001101000 )
b001110010 *
b01101000 ,
b01110010 -
#629
0#
#630
1#
b001100010 )
b001101101 *
b01100010 ,
b01101101 -
#631
0#
#632
1#
b001011110 )
b001101000 *
b01011110 ,
b01101000 -
#633
0#
#634
1#
b001011101 )
b001100010 *
b01011101 ,
b01100010 -
#635
0#
#636
1#
b001100001 )
b001011110 *
b01100001 ,
b01011110 -
#637
0#
#638
1#
b000000101 (
b001011101 *
b01011101 -
#639
0#
#640
1#
b001101000 )
b001100001 *
b01101000 ,
b01100001 -
#641
0#
#642
1#
b000000011 (
b001101011 )
b01101011 ,
#643
0#
#644
1#
b000000000 (
b001101100 )
b001101000 *
b01101100 ,
b01101000 -
#645
0#
#646
1#
b001101111 )
b001101011 *
b01101111 ,
b01101011 -
#647
0#
#648
1#
b001101101 )
b001101100 *
b01101101 ,
b01101100 -
#649
0#
